aws_textract/__init__.py
aws_textract/_version.py
aws_textract/api.py
aws_textract/paths.py
aws_textract/better_boto/__init__.py
aws_textract/better_boto/api.py
aws_textract/better_boto/async_api.py
aws_textract/docs/__init__.py
aws_textract/response/__init__.py
aws_textract/response/api.py
aws_textract/response/contants.py
aws_textract/response/merge.py
aws_textract/response/utils.py
aws_textract/tests/__init__.py
aws_textract/tests/helper.py
aws_textract/vendor/__init__.py
aws_textract/vendor/better_dataclasses.py
aws_textract/vendor/pytest_cov_helper.py
aws_textract/vendor/waiter.py
aws_textract-0.3.1.dist-info/AUTHORS.rst
aws_textract-0.3.1.dist-info/LICENSE.txt
aws_textract-0.3.1.dist-info/METADATA
aws_textract-0.3.1.dist-info/WHEEL
aws_textract-0.3.1.dist-info/top_level.txt
aws_textract-0.3.1.dist-info/RECORD
